sagecoffee/__init__.py
sagecoffee/auth.py
sagecoffee/client.py
sagecoffee/http_api.py
sagecoffee/logging.py
sagecoffee/models.py
sagecoffee/store.py
sagecoffee/ws_client.py
sagecoffee/cli/__init__.py
sagecoffee/cli/main.py
sagecoffee-0.1.1.dist-info/METADATA
sagecoffee-0.1.1.dist-info/WHEEL
sagecoffee-0.1.1.dist-info/entry_points.txt
sagecoffee-0.1.1.dist-info/licenses/LICENSE
sagecoffee-0.1.1.dist-info/RECORD
