Metadata-Version: 2.4
Name: sagecoffee
Version: 0.1.1
Summary: Python library and CLI for controlling Breville/Sage coffee machines
Project-URL: Homepage, https://github.com/simonjgreen/sagecoffee
Project-URL: Repository, https://github.com/simonjgreen/sagecoffee
Author-email: Simon Green <simon@sjg.io>
License-Expression: MIT
License-File: LICENSE
Keywords: breville,coffee,iot,sage,smart-home
Classifier: Development Status :: 3 - Alpha
Classifier: Intended Audience :: Developers
Classifier: License :: OSI Approved :: MIT License
Classifier: Programming Language :: Python :: 3
Classifier: Programming Language :: Python :: 3.11
Classifier: Programming Language :: Python :: 3.12
Classifier: Topic :: Home Automation
Requires-Python: >=3.11
Requires-Dist: httpx>=0.27.0
Requires-Dist: pydantic>=2.0
Requires-Dist: tomli-w>=1.0.0
Requires-Dist: tomli>=2.0.0; python_version < '3.11'
Requires-Dist: typer[all]>=0.9.0
Requires-Dist: websockets>=12.0
Provides-Extra: dev
Requires-Dist: black>=24.0.0; extra == 'dev'
Requires-Dist: mypy>=1.8.0; extra == 'dev'
Requires-Dist: pytest-asyncio>=0.23.0; extra == 'dev'
Requires-Dist: pytest>=8.0.0; extra == 'dev'
Requires-Dist: ruff>=0.2.0; extra == 'dev'
